LICENSE.txt
evo_package_huggingface/__init__.py
evo_package_huggingface/automation/api.yaml
evo_package_huggingface/automation/entity.yaml
evo_package_huggingface/control/CHuggingfaceChatApi.py
evo_package_huggingface/control/CHuggingfaceImage.py
evo_package_huggingface/control/__init__.py
evo_package_huggingface/entity/EHuggingfaceChatInput.py
evo_package_huggingface/entity/__init__.py
evo_package_huggingface/utility/UHuggingfaceChatApi.py
evo_package_huggingface/utility/__init__.py
evo_package_huggingface-2024.10.191021.dist-info/LICENSE.txt
evo_package_huggingface-2024.10.191021.dist-info/METADATA
evo_package_huggingface-2024.10.191021.dist-info/WHEEL
evo_package_huggingface-2024.10.191021.dist-info/RECORD
