Metadata-Version: 2.1
Name: evo-package-huggingface
Version: 2024.10.191021
Summary: evo-package-huggingface python
License: CC BY-NC-ND 4.0
Author: cyborg-ai-git
Author-email: 129898917+cyborg-ai-git@users.noreply.github.com
Requires-Python: >=3.10,<4.0
Classifier: License :: Other/Proprietary License
Classifier: Programming Language :: Python :: 3
Classifier: Programming Language :: Python :: 3.10
Classifier: Programming Language :: Python :: 3.11
Classifier: Programming Language :: Python :: 3.12
Requires-Dist: accelerate (>=0.33.0,<0.34.0)
Requires-Dist: evo-framework
Requires-Dist: evo-package-chat
Requires-Dist: hugchat (>=0.4.10,<0.5.0)
Requires-Dist: sentencepiece (>=0.2.0,<0.3.0)
Requires-Dist: torch (>=2.3.1,<3.0.0)
Requires-Dist: transformers (>=4.43.3,<5.0.0)
